chineseflashcards/__init__.py
chineseflashcards/__main__.py
chineseflashcards/add_pinyin_diacritics_and_color.js
chineseflashcards/cards.css
chineseflashcards/cedict.txt
chineseflashcards/fields.json
chineseflashcards/templates.yaml
chineseflashcards/version.py
chineseflashcards-0.4.7.dist-info/LICENSE.md
chineseflashcards-0.4.7.dist-info/METADATA
chineseflashcards-0.4.7.dist-info/WHEEL
chineseflashcards-0.4.7.dist-info/top_level.txt
chineseflashcards-0.4.7.dist-info/RECORD
