Metadata-Version: 2.1
Name: chineseflashcards
Version: 0.4.7
Summary: Create Chinese flashcards for Anki using the genanki lib
Home-page: http://github.com/kerrickstaley/chineseflashcards
Author: Kerrick Staley
Author-email: k@kerrickstaley.com
License: MIT
License-File: LICENSE.md
Requires-Dist: genanki >=0.4
Requires-Dist: pyyaml >=3.12
